{
  "hash": "68fd03f467164afd37e2c77ef4d72111",
  "result": {
    "engine": "jupyter",
    "markdown": "---\ntitle: \"Xuliqin homework for lecture 2-pet names\"\noutput: \n  html_document:\n    toc: FALSE\n---\n\n::: {#0dac477f .cell execution_count=1}\n``` {.python .cell-code}\nimport pandas as pd\ndf = pd.read_csv('./file/seattle_pet_licenses.csv')\ndf\n```\n\n::: {.cell-output .cell-output-display execution_count=4}\n```{=html}\n<div>\n<style scoped>\n    .dataframe tbody tr th:only-of-type {\n        vertical-align: middle;\n    }\n\n    .dataframe tbody tr th {\n        vertical-align: top;\n    }\n\n    .dataframe thead th {\n        text-align: right;\n    }\n</style>\n<table border=\"1\" class=\"dataframe\">\n  <thead>\n    <tr style=\"text-align: right;\">\n      <th></th>\n      <th>animal_s_name</th>\n      <th>license_issue_date</th>\n      <th>license_number</th>\n      <th>primary_breed</th>\n      <th>secondary_breed</th>\n      <th>species</th>\n      <th>zip_code</th>\n    </tr>\n  </thead>\n  <tbody>\n    <tr>\n      <th>0</th>\n      <td>Ozzy</td>\n      <td>2005-03-29T00:00:00.000</td>\n      <td>130651.0</td>\n      <td>Dachshund, Standard Smooth Haired</td>\n      <td>NaN</td>\n      <td>Dog</td>\n      <td>98104</td>\n    </tr>\n    <tr>\n      <th>1</th>\n      <td>Jack</td>\n      <td>2009-12-23T00:00:00.000</td>\n      <td>898148.0</td>\n      <td>Schnauzer, Miniature</td>\n      <td>Terrier, Rat</td>\n      <td>Dog</td>\n      <td>98107</td>\n    </tr>\n    <tr>\n      <th>2</th>\n      <td>Ginger</td>\n      <td>2006-01-20T00:00:00.000</td>\n      <td>29654.0</td>\n      <td>Retriever, Golden</td>\n      <td>Retriever, Labrador</td>\n      <td>Dog</td>\n      <td>98117</td>\n    </tr>\n    <tr>\n      <th>3</th>\n      <td>Pepper</td>\n      <td>2006-02-07T00:00:00.000</td>\n      <td>75432.0</td>\n      <td>Manx</td>\n      <td>Mix</td>\n      <td>Cat</td>\n      <td>98103</td>\n    </tr>\n    <tr>\n      <th>4</th>\n      <td>Addy</td>\n      <td>2006-08-04T00:00:00.000</td>\n      <td>729899.0</td>\n      <td>Retriever, Golden</td>\n      <td>NaN</td>\n      <td>Dog</td>\n      <td>98105</td>\n    </tr>\n    <tr>\n      <th>...</th>\n      <td>...</td>\n      <td>...</td>\n      <td>...</td>\n      <td>...</td>\n      <td>...</td>\n      <td>...</td>\n      <td>...</td>\n    </tr>\n    <tr>\n      <th>66037</th>\n      <td>Lily</td>\n      <td>2016-12-27T00:00:00.000</td>\n      <td>NaN</td>\n      <td>Domestic Shorthair</td>\n      <td>Mix</td>\n      <td>Cat</td>\n      <td>98117</td>\n    </tr>\n    <tr>\n      <th>66038</th>\n      <td>Ellie</td>\n      <td>2016-11-29T00:00:00.000</td>\n      <td>NaN</td>\n      <td>German Shepherd</td>\n      <td>Mix</td>\n      <td>Dog</td>\n      <td>98105</td>\n    </tr>\n    <tr>\n      <th>66039</th>\n      <td>Sammy</td>\n      <td>2016-12-05T00:00:00.000</td>\n      <td>NaN</td>\n      <td>Terrier</td>\n      <td>Maltese</td>\n      <td>Dog</td>\n      <td>98105</td>\n    </tr>\n    <tr>\n      <th>66040</th>\n      <td>Buddy</td>\n      <td>2016-12-06T00:00:00.000</td>\n      <td>NaN</td>\n      <td>Bullmastiff</td>\n      <td>Mix</td>\n      <td>Dog</td>\n      <td>98105</td>\n    </tr>\n    <tr>\n      <th>66041</th>\n      <td>Aku</td>\n      <td>2016-12-07T00:00:00.000</td>\n      <td>NaN</td>\n      <td>Chihuahua, Short Coat</td>\n      <td>Terrier</td>\n      <td>Dog</td>\n      <td>98106</td>\n    </tr>\n  </tbody>\n</table>\n<p>66042 rows × 7 columns</p>\n</div>\n```\n:::\n:::\n\n\n::: {#2dd1989a .cell execution_count=2}\n``` {.python .cell-code}\ndf.info()\n```\n\n::: {.cell-output .cell-output-stdout}\n```\n<class 'pandas.core.frame.DataFrame'>\nRangeIndex: 66042 entries, 0 to 66041\nData columns (total 7 columns):\n #   Column              Non-Null Count  Dtype  \n---  ------              --------------  -----  \n 0   animal_s_name       64685 non-null  object \n 1   license_issue_date  66042 non-null  object \n 2   license_number      43885 non-null  float64\n 3   primary_breed       66042 non-null  object \n 4   secondary_breed     22538 non-null  object \n 5   species             66042 non-null  object \n 6   zip_code            65884 non-null  object \ndtypes: float64(1), object(6)\nmemory usage: 3.5+ MB\n```\n:::\n:::\n\n\n::: {#1f03060c .cell execution_count=3}\n``` {.python .cell-code}\ndf['animal_s_name'].value_counts()\n```\n\n::: {.cell-output .cell-output-display execution_count=6}\n```\nanimal_s_name\nLucy          566\nBella         451\nCharlie       447\nMax           374\nLuna          361\n             ... \nManasseh        1\nTaba            1\nMiriam          1\nNumber Six      1\nRollins         1\nName: count, Length: 15795, dtype: int64\n```\n:::\n:::\n\n\n",
    "supporting": [
      "homework2_files"
    ],
    "filters": [],
    "includes": {
      "include-in-header": [
        "<script src=\"https://cdnjs.cloudflare.com/ajax/libs/require.js/2.3.6/require.min.js\" integrity=\"sha512-c3Nl8+7g4LMSTdrm621y7kf9v3SDPnhxLNhcjFJbKECVnmZHTdo+IRO05sNLTH/D3vA6u1X32ehoLC7WFVdheg==\" crossorigin=\"anonymous\"></script>\n<script src=\"https://cdnjs.cloudflare.com/ajax/libs/jquery/3.5.1/jquery.min.js\" integrity=\"sha512-bLT0Qm9VnAYZDflyKcBaQ2gg0hSYNQrJ8RilYldYQ1FxQYoCLtUjuuRuZo+fjqhx/qtq/1itJ0C2ejDxltZVFg==\" crossorigin=\"anonymous\" data-relocate-top=\"true\"></script>\n<script type=\"application/javascript\">define('jquery', [],function() {return window.jQuery;})</script>\n"
      ]
    }
  }
}